perovskite_assessment/__init__.py
perovskite_assessment/input_generation.py
perovskite_assessment/output_extraction.py
perovskite_assessment/overpotential.py
perovskite_assessment/structure_generation.py
assessPEROVSKITE-0.1.dist-info/METADATA
assessPEROVSKITE-0.1.dist-info/WHEEL
assessPEROVSKITE-0.1.dist-info/entry_points.txt
assessPEROVSKITE-0.1.dist-info/top_level.txt
assessPEROVSKITE-0.1.dist-info/RECORD
